carrot/__init__.py
carrot/_version.py
carrot/analyses/__init__.py
carrot/analyses/example_serology.py
carrot/cdm/__init__.py
carrot/cdm/decorators.py
carrot/cdm/model.py
carrot/cdm/operations.py
carrot/cdm/classes/__init__.py
carrot/cdm/objects/__init__.py
carrot/cdm/objects/common.py
carrot/cdm/objects/versions/__init__.py
carrot/cdm/objects/versions/v5_3_1/__init__.py
carrot/cdm/objects/versions/v5_3_1/condition_occurrence.py
carrot/cdm/objects/versions/v5_3_1/death.py
carrot/cdm/objects/versions/v5_3_1/drug_exposure.py
carrot/cdm/objects/versions/v5_3_1/measurement.py
carrot/cdm/objects/versions/v5_3_1/observation.py
carrot/cdm/objects/versions/v5_3_1/person.py
carrot/cdm/objects/versions/v5_3_1/procedure_occurrence.py
carrot/cdm/objects/versions/v5_3_1/specimen.py
carrot/cdm/objects/versions/v5_3_1/visit_occurrence.py
carrot/cli/__init__.py
carrot/cli/cli.py
carrot/cli/subcommands/__init__.py
carrot/cli/subcommands/airflow.py
carrot/cli/subcommands/display.py
carrot/cli/subcommands/etl.py
carrot/cli/subcommands/generate.py
carrot/cli/subcommands/get.py
carrot/cli/subcommands/info.py
carrot/cli/subcommands/pseudonymise.py
carrot/cli/subcommands/run.py
carrot/cli/subcommands/search.py
carrot/data/config/omop.json
carrot/data/example/sample_config/lion_structural_mapping.json
carrot/data/example/sample_input_data/demo.csv
carrot/data/example/sample_input_data/questions.csv
carrot/data/test/automation/example-full.yml
carrot/data/test/automation/example.yml
carrot/data/test/expected_outputs/condition_occurrence.tsv
carrot/data/test/expected_outputs/measurement.tsv
carrot/data/test/expected_outputs/observation.tsv
carrot/data/test/expected_outputs/person.tsv
carrot/data/test/expected_outputs/person_ids.tsv
carrot/data/test/expected_outputs/summary.tsv
carrot/data/test/inputs/Covid19_test.csv
carrot/data/test/inputs/Demographics.csv
carrot/data/test/inputs/Symptoms.csv
carrot/data/test/inputs/covid19_antibody.csv
carrot/data/test/inputs/vaccine.csv
carrot_cdm-0.745.dist-info/LICENSE
carrot_cdm-0.745.dist-info/METADATA
carrot_cdm-0.745.dist-info/WHEEL
carrot_cdm-0.745.dist-info/entry_points.txt
carrot_cdm-0.745.dist-info/top_level.txt
carrot_cdm-0.745.dist-info/RECORD
